setup.py
after_response/__init__.py
after_response/decorators.py
after_response/models.py
after_response/signals.py
after_response/store.py
after_response/tests.py
django_after_response.egg-info/PKG-INFO
django_after_response.egg-info/SOURCES.txt
django_after_response.egg-info/dependency_links.txt
django_after_response.egg-info/requires.txt
django_after_response.egg-info/top_level.txt