Metadata-Version: 1.0
Name: django-after-response
Version: 0.1.0
Summary: Simple asynchronous execution
Home-page: http://github.com/defrex/django-after-response/
Author: Aron Jones
Author-email: aron.jones@gmail.com
License: MIT
Platform: UNKNOWN
